odoo/addons/website_sale_acquirer_confirm_order/README.rst
odoo/addons/website_sale_acquirer_confirm_order/__init__.py
odoo/addons/website_sale_acquirer_confirm_order/__manifest__.py
odoo/addons/website_sale_acquirer_confirm_order/controllers/__init__.py
odoo/addons/website_sale_acquirer_confirm_order/controllers/main.py
odoo/addons/website_sale_acquirer_confirm_order/i18n/it.po
odoo/addons/website_sale_acquirer_confirm_order/i18n/website_sale_acquirer_confirm_order.pot
odoo/addons/website_sale_acquirer_confirm_order/models/__init__.py
odoo/addons/website_sale_acquirer_confirm_order/models/payment_provider.py
odoo/addons/website_sale_acquirer_confirm_order/readme/CONTEXT.md
odoo/addons/website_sale_acquirer_confirm_order/readme/CONTRIBUTORS.md
odoo/addons/website_sale_acquirer_confirm_order/readme/DESCRIPTION.md
odoo/addons/website_sale_acquirer_confirm_order/readme/USAGE.md
odoo/addons/website_sale_acquirer_confirm_order/static/description/icon.png
odoo/addons/website_sale_acquirer_confirm_order/static/description/index.html
odoo/addons/website_sale_acquirer_confirm_order/static/src/js/website_sale_acquirer_confirm_order_tour.esm.js
odoo/addons/website_sale_acquirer_confirm_order/tests/__init__.py
odoo/addons/website_sale_acquirer_confirm_order/tests/test_website_sale_acquirer_confirm_order.py
odoo/addons/website_sale_acquirer_confirm_order/views/payment_provider_views.xml
odoo_addon_website_sale_acquirer_confirm_order-18.0.1.0.0.4.dist-info/METADATA
odoo_addon_website_sale_acquirer_confirm_order-18.0.1.0.0.4.dist-info/WHEEL
odoo_addon_website_sale_acquirer_confirm_order-18.0.1.0.0.4.dist-info/top_level.txt
odoo_addon_website_sale_acquirer_confirm_order-18.0.1.0.0.4.dist-info/RECORD
